ovos_gguf_translate/__init__.py
ovos_gguf_translate/version.py
ovos_gguf_translate-0.0.1.dist-info/METADATA
ovos_gguf_translate-0.0.1.dist-info/WHEEL
ovos_gguf_translate-0.0.1.dist-info/top_level.txt
ovos_gguf_translate-0.0.1.dist-info/RECORD
