Metadata-Version: 2.1
Name: ovos-gguf-translate
Version: 0.0.1
Summary: UNKNOWN
Home-page: https://github.com/TigreGotico/ovos_gguf_translate
Author: jarbasAI
Author-email: jarbasai@mailfence.com
License: MIT
Platform: UNKNOWN
Requires-Dist: langcodes[data]
